setup.py
distributions/Binomialdistribution.py
distributions/Gaussiandistribution.py
distributions/Generaldistribution.py
distributions/__init__.py
jaime_distributions.egg-info/PKG-INFO
jaime_distributions.egg-info/SOURCES.txt
jaime_distributions.egg-info/dependency_links.txt
jaime_distributions.egg-info/not-zip-safe
jaime_distributions.egg-info/top_level.txt